appsettingsreader/__init__.py
appsettingsreader/reader.py
appsettingsreader-1.0.0.dist-info/LICENSE.txt
appsettingsreader-1.0.0.dist-info/METADATA
appsettingsreader-1.0.0.dist-info/WHEEL
appsettingsreader-1.0.0.dist-info/top_level.txt
appsettingsreader-1.0.0.dist-info/RECORD
