Metadata-Version: 2.1
Name: appsettingsreader
Version: 1.0.0
Summary: Read appSettings values from .NET XML config files
Home-page: https://github.com/isisbusapps/BISAppSettingsReader
Author: STFC User Programme Software
Author-email: FacilitiesBusinessSystem@stfc.ac.uk
License: UNKNOWN
Platform: UNKNOWN
Classifier: Programming Language :: Python :: 3
Classifier: License :: OSI Approved :: MIT License
Classifier: Operating System :: OS Independent
Classifier: Topic :: Text Processing :: Markup :: XML
Requires-Python: >=3.7
License-File: LICENSE.txt
